mango/__init__.py
mango/agent/__init__.py
mango/agent/core.py
mango/agent/role.py
mango/container/__init__.py
mango/container/core.py
mango/container/external_coupling.py
mango/container/factory.py
mango/container/mqtt.py
mango/container/protocol.py
mango/container/tcp.py
mango/messages/__init__.py
mango/messages/acl_message.proto
mango/messages/acl_message_pb2.py
mango/messages/codecs.py
mango/messages/message.py
mango/messages/other_proto_msgs.proto
mango/messages/other_proto_msgs_pb2.py
mango/modules/__init__.py
mango/modules/base_module.py
mango/modules/mqtt_module.py
mango/modules/rabbit_module.py
mango/modules/zero_module.py
mango/util/__init__.py
mango/util/clock.py
mango/util/distributed_clock.py
mango/util/distributed_termination.py
mango/util/multiprocessing.py
mango/util/scheduling.py
mango/util/termination_detection.py
mango_agents_assume-1.2.0.post1.dist-info/LICENSE
mango_agents_assume-1.2.0.post1.dist-info/METADATA
mango_agents_assume-1.2.0.post1.dist-info/WHEEL
mango_agents_assume-1.2.0.post1.dist-info/top_level.txt
mango_agents_assume-1.2.0.post1.dist-info/RECORD
