Metadata-Version: 2.1
Name: mango-agents-assume
Version: 1.2.0.post1
Summary: Modular Python Agent Framework - Temporary Fork of mango for development purpose
Author-email: Mango Developers <mango@offis.de>, Florian Maurer <fmaurer@disroot.org>
License: MIT License
Project-URL: Homepage, https://mango-agents.readthedocs.io/
Project-URL: Repository, https://github.com/maurerle/mango
Keywords: agent based simulation,simulation
Classifier: Development Status :: 4 - Beta
Classifier: Intended Audience :: Developers
Classifier: License :: OSI Approved :: MIT License
Classifier: Operating System :: OS Independent
Classifier: Framework :: AsyncIO
Classifier: Topic :: Scientific/Engineering
Classifier: Topic :: Software Development :: Libraries :: Python Modules
Classifier: Programming Language :: Python :: 3.9
Classifier: Programming Language :: Python :: 3.10
Classifier: Programming Language :: Python :: 3.11
Classifier: Programming Language :: Python :: 3.12
Requires-Python: >=3.9
License-File: LICENSE
Requires-Dist: dill >=0.3.8
Requires-Dist: msgspec >=0.18.6
Requires-Dist: paho-mqtt >=2.1.0
Requires-Dist: protobuf ==5.27.2
Requires-Dist: python-dateutil >=2.9.0
Provides-Extra: dev
Requires-Dist: black ; extra == 'dev'
Requires-Dist: isort ; extra == 'dev'
Requires-Dist: pytest ; extra == 'dev'
Requires-Dist: pytest-cov ; extra == 'dev'
Requires-Dist: pytest-asyncio ; extra == 'dev'
